django_wikidata_api/__init__.py
django_wikidata_api/admin.py
django_wikidata_api/apps.py
django_wikidata_api/constants.py
django_wikidata_api/exceptions.py
django_wikidata_api/fields.py
django_wikidata_api/models.py
django_wikidata_api/serializers.py
django_wikidata_api/urls.py
django_wikidata_api/utils.py
django_wikidata_api/views.py
django_wikidata_api/viewsets.py
django_wikidata_api-0.0.14.dist-info/LICENSE
django_wikidata_api-0.0.14.dist-info/METADATA
django_wikidata_api-0.0.14.dist-info/WHEEL
django_wikidata_api-0.0.14.dist-info/top_level.txt
django_wikidata_api-0.0.14.dist-info/RECORD
