Metadata-Version: 2.1
Name: django-wikidata-api
Version: 0.0.14
Summary: Python Package for interfacing with Wikidata within a Django App
Home-page: https://github.com/kennethsn/django-wikidata-api
Author: Kenneth Seals-Nutt
Author-email: kenneth@seals-nutt.com
License: AGPL-3.0
Classifier: Development Status :: 3 - Alpha
Classifier: Natural Language :: English
Classifier: Operating System :: MacOS :: MacOS X
Classifier: Programming Language :: Python :: 3.6
Classifier: Programming Language :: Python :: 3.7
Classifier: Programming Language :: Python :: 3.8
Classifier: Framework :: Django
Classifier: Framework :: Django :: 2.2
Classifier: Framework :: Django :: 3.0
Classifier: License :: OSI Approved :: GNU Affero General Public License v3
Requires-Python: >=3.6
License-File: LICENSE
Requires-Dist: Django (>=2.2)
Requires-Dist: djangorestframework (>=3.11.0)
Requires-Dist: drf-yasg (>=1.17)
Requires-Dist: mock
Requires-Dist: requests
Requires-Dist: wikidataintegrator (>=0.4.2)
Requires-Dist: pandas (>=0.25.2)
Requires-Dist: tqdm (>=4.36.1)
